db_az_sync_provider-0.1.6.dist-info/METADATA
db_az_sync_provider-0.1.6.dist-info/WHEEL
db_az_sync_provider-0.1.6.dist-info/entry_points.txt
db_az_sync_provider/__init__.py
db_az_sync_provider/azure_identity.py
db_az_sync_provider/databricks_identity.py
db_az_sync_provider/main.py
db_az_sync_provider/one_way_match.py
db_az_sync_provider/sync_classes.py
db_az_sync_provider/yaml_parser.py
db_az_sync_provider-0.1.6.dist-info/RECORD
