Metadata-Version: 2.1
Name: db-az-sync-provider
Version: 0.1.6
Summary: A PDM package to sync Azure users, roles and service principals to Databricks
Author-Email: Nicolas <nicolas.jankelevitch@dataroots.io>, Bram <bram.decoster@dataroots.io>, Adrien <adrien@dataroots.io>, Xuyao <xuyao@dataroots.io>, Sam <sam@dataroots.io>
License: MIT
Project-URL: Homepage, https://github.com/datarootsio/databricks-azure-ad-sync-provider
Requires-Python: >=3.9
Requires-Dist: azure-identity>=1.15.0
Requires-Dist: databricks-sdk>=0.17.0
Requires-Dist: msgraph-sdk>=1.0.0
Requires-Dist: ConfigParser>=6.0.0
Requires-Dist: pyyaml>=6.0.1
Requires-Dist: pytest>=7.4.4
